pyeuropepmc/__init__.py
pyeuropepmc/builders/__init__.py
pyeuropepmc/builders/from_parser.py
pyeuropepmc/cache/cache.py
pyeuropepmc/clients/__init__.py
pyeuropepmc/clients/article.py
pyeuropepmc/clients/ftp_downloader.py
pyeuropepmc/clients/fulltext.py
pyeuropepmc/clients/search.py
pyeuropepmc/core/__init__.py
pyeuropepmc/core/base.py
pyeuropepmc/core/error_codes.py
pyeuropepmc/core/exceptions.py
pyeuropepmc/enrichment/__init__.py
pyeuropepmc/enrichment/base.py
pyeuropepmc/enrichment/batch_enricher.py
pyeuropepmc/enrichment/config.py
pyeuropepmc/enrichment/crossref.py
pyeuropepmc/enrichment/datacite.py
pyeuropepmc/enrichment/enricher.py
pyeuropepmc/enrichment/file_enricher.py
pyeuropepmc/enrichment/merger.py
pyeuropepmc/enrichment/openalex.py
pyeuropepmc/enrichment/reporter.py
pyeuropepmc/enrichment/ror.py
pyeuropepmc/enrichment/semantic_scholar.py
pyeuropepmc/enrichment/unpaywall.py
pyeuropepmc/mappers/__init__.py
pyeuropepmc/mappers/config_utils.py
pyeuropepmc/mappers/converters.py
pyeuropepmc/mappers/exceptions.py
pyeuropepmc/mappers/processors.py
pyeuropepmc/mappers/provenance.py
pyeuropepmc/mappers/quality_metrics.py
pyeuropepmc/mappers/rdf_mapper.py
pyeuropepmc/mappers/rdf_utils.py
pyeuropepmc/mappers/rml_rdfizer.py
pyeuropepmc/mappers/semantic_enrichment.py
pyeuropepmc/mappers/validation.py
pyeuropepmc/mappers/validators.py
pyeuropepmc/models/__init__.py
pyeuropepmc/models/author.py
pyeuropepmc/models/base.py
pyeuropepmc/models/figure.py
pyeuropepmc/models/grant.py
pyeuropepmc/models/institution.py
pyeuropepmc/models/journal.py
pyeuropepmc/models/mesh.py
pyeuropepmc/models/paper.py
pyeuropepmc/models/reference.py
pyeuropepmc/models/scholarly_work.py
pyeuropepmc/models/section.py
pyeuropepmc/models/table.py
pyeuropepmc/models/utils.py
pyeuropepmc/pipeline.py
pyeuropepmc/processing/__init__.py
pyeuropepmc/processing/analytics.py
pyeuropepmc/processing/config/__init__.py
pyeuropepmc/processing/config/document_schema.py
pyeuropepmc-1.14.0.dist-info/METADATA
pyeuropepmc-1.14.0.dist-info/WHEEL
pyeuropepmc-1.14.0.dist-info/licenses/LICENSE
pyeuropepmc-1.14.0.dist-info/RECORD
