Metadata-Version: 2.4
Name: pyeuropepmc
Version: 1.14.0
Summary: A Python package for working with the Europe PMC API to search and retrieve scientific literature.
License: file:LICENSE
License-File: LICENSE
Keywords: europe-pmc,pubmed,literature,api,scientific
Author: Jonas Heinicke (HZI)
Author-email: jonas.heinicke@helmholtz-hzi.de
Requires-Python: >=3.10,<4.0
Classifier: Development Status :: 5 - Production/Stable
Classifier: Intended Audience :: Science/Research
Classifier: License :: OSI Approved :: MIT License
Classifier: Operating System :: OS Independent
Classifier: Programming Language :: Python :: 3
Classifier: Programming Language :: Python :: 3.10
Classifier: Programming Language :: Python :: 3.11
Classifier: Programming Language :: Python :: 3.12
Classifier: Topic :: Scientific/Engineering :: Bio-Informatics
Requires-Dist: backoff (>=2.2.1,<3.0.0)
Requires-Dist: beautifulsoup4 (>=4.13.5,<5.0.0)
Requires-Dist: cachetools (>=6.2.1,<7.0.0)
Requires-Dist: cryptography (>=46.0.3,<47.0.0)
Requires-Dist: defusedxml (>=0.7.1,<0.8.0)
Requires-Dist: diskcache (>=5.6.3,<6.0.0)
Requires-Dist: flask (>=3.1.1,<4.0.0)
Requires-Dist: ipykernel (>=6.7)
Requires-Dist: ipython (>=7.30)
Requires-Dist: ipywidgets (>=7.6)
Requires-Dist: jupyterlab (>=3.2)
Requires-Dist: matplotlib (>=3.7.0,<4.0.0)
Requires-Dist: notebook (>=6.4)
Requires-Dist: numpy (>=1.21)
Requires-Dist: pandas (>=1.4)
Requires-Dist: python-dotenv (>=0.19)
Requires-Dist: rapidfuzz (>=2.15.0,<3.0.0)
Requires-Dist: rdfizer (>=4.7.5.12.13,<5.0.0.0.0)
Requires-Dist: rdflib (>=6.0)
Requires-Dist: rdflib-jsonld (>=0.5)
Requires-Dist: requests (>=2.32.5,<3.0.0)
Requires-Dist: requests-cache (>=1.2.1,<2.0.0)
Requires-Dist: seaborn (>=0.12.0,<0.13.0)
Requires-Dist: search-query (>=0.13.0,<0.14.0)
Requires-Dist: tabulate (>=0.9.0,<0.10.0)
Requires-Dist: tornado (>=6.5.1,<7.0.0)
Requires-Dist: tqdm (>=4.67.1,<5.0.0)
Requires-Dist: typer (>=0.12.5,<0.13.0)
Requires-Dist: xlsxwriter (>=3.2.9,<4.0.0)
Project-URL: Homepage, https://github.com/JonasHeinickeBio/pyEuropePMC
Project-URL: Repository, https://github.com/JonasHeinickeBio/pyEuropePMC
